lfsr_tools/__init__.py
lfsr_tools/_version.py
lfsr_tools/berlekamp_massey.py
lfsr_tools/lfsr.py
lfsr_tools/lfsr_config.py
lfsr_tools/utils.py
lfsr_tools-0.0.1.dist-info/LICENSE
lfsr_tools-0.0.1.dist-info/METADATA
lfsr_tools-0.0.1.dist-info/WHEEL
lfsr_tools-0.0.1.dist-info/top_level.txt
lfsr_tools-0.0.1.dist-info/RECORD
