Metadata-Version: 2.1
Name: lfsr-tools
Version: 0.0.1
Summary: Tools for pseudo-random number sequence generation and LFSR recovery.
Author-email: jroth2858 <jroth2858@users.noreply.github.com>
Project-URL: Homepage, https://github.com/jroth2858/lfsr-tools
Project-URL: Issues, https://github.com/jroth2858/lfsr-tools/issues
Classifier: Programming Language :: Python :: 3
Classifier: License :: OSI Approved :: MIT License
Classifier: Operating System :: OS Independent
Requires-Python: >=3.9
License-File: LICENSE
